{
  "version": 2,
  "exportedAt": "2026-05-12T00:30:33.455Z",
  "events": [
    {
      "id": 1,
      "date": "2026-05-08",
      "time": "",
      "title": "Festival Rugby",
      "type": "sports",
      "classes": [
        "5A",
        "5B",
        "6A",
        "6B"
      ],
      "groupId": null,
      "rangeStart": null,
      "rangeEnd": null,
      "rangePosition": null
    },
    {
      "id": 2,
      "date": "2026-05-08",
      "time": "",
      "title": "Festival Hockey",
      "type": "sports",
      "classes": [
        "5A",
        "5B",
        "6A",
        "6B"
      ],
      "groupId": null,
      "rangeStart": null,
      "rangeEnd": null,
      "rangePosition": null
    },
    {
      "id": 3,
      "date": "2026-05-09",
      "time": "",
      "title": "Fest. Hockey/Rugby",
      "type": "sports",
      "classes": [
        "3A",
        "3B",
        "4A",
        "4B"
      ],
      "groupId": null,
      "rangeStart": null,
      "rangeEnd": null,
      "rangePosition": null
    },
    {
      "id": 4,
      "date": "2026-05-11",
      "time": "",
      "title": "Visita St Matthew's",
      "type": "activity",
      "classes": [
        "8A",
        "8B"
      ],
      "groupId": null,
      "rangeStart": null,
      "rangeEnd": null,
      "rangePosition": null
    },
    {
      "id": 5,
      "date": "2026-05-12",
      "time": "",
      "title": "Visita St Matthew's",
      "type": "activity",
      "classes": [
        "8A",
        "8B"
      ],
      "groupId": null,
      "rangeStart": null,
      "rangeEnd": null,
      "rangePosition": null
    },
    {
      "id": 6,
      "date": "2026-05-13",
      "time": "",
      "title": "Visita St Matthew's",
      "type": "activity",
      "classes": [
        "8A",
        "8B"
      ],
      "groupId": null,
      "rangeStart": null,
      "rangeEnd": null,
      "rangePosition": null
    },
    {
      "id": 7,
      "date": "2026-05-14",
      "time": "",
      "title": "Visita St Matthew's",
      "type": "activity",
      "classes": [
        "8A",
        "8B"
      ],
      "groupId": null,
      "rangeStart": null,
      "rangeEnd": null,
      "rangePosition": null
    },
    {
      "id": 8,
      "date": "2026-05-15",
      "time": "",
      "title": "Visita St Matthew's",
      "type": "activity",
      "classes": [
        "8A",
        "8B"
      ],
      "groupId": null,
      "rangeStart": null,
      "rangeEnd": null,
      "rangePosition": null
    },
    {
      "id": 9,
      "date": "2026-05-16",
      "time": "",
      "title": "Visita St Matthew's",
      "type": "activity",
      "classes": [
        "8A",
        "8B"
      ],
      "groupId": null,
      "rangeStart": null,
      "rangeEnd": null,
      "rangePosition": null
    },
    {
      "id": 10,
      "date": "2026-05-23",
      "time": "",
      "title": "Deportes: por confirmar",
      "type": "sports",
      "classes": [
        "5A",
        "5B",
        "6A",
        "6B",
        "7A",
        "7B",
        "8A",
        "8B",
        "IA",
        "IB",
        "IIA",
        "IIB",
        "IIIA",
        "IIIB",
        "IVA",
        "IVB"
      ],
      "groupId": null,
      "rangeStart": null,
      "rangeEnd": null,
      "rangePosition": null
    },
    {
      "id": 11,
      "date": "2026-06-19",
      "time": "",
      "title": "Torneo Rugby",
      "type": "sports",
      "classes": [
        "IA",
        "IB",
        "IIA",
        "IIB",
        "IIIA",
        "IIIB",
        "IVA",
        "IVB"
      ],
      "groupId": null,
      "rangeStart": null,
      "rangeEnd": null,
      "rangePosition": null
    },
    {
      "id": 12,
      "date": "2026-07-04",
      "time": "",
      "title": "Bilateral: St.Gabriel's",
      "type": "sports",
      "classes": [
        "5A",
        "5B",
        "6A",
        "6B",
        "7A",
        "7B",
        "8A",
        "8B"
      ],
      "groupId": null,
      "rangeStart": null,
      "rangeEnd": null,
      "rangePosition": null
    },
    {
      "id": 13,
      "date": "2026-07-04",
      "time": "",
      "title": "Bilateral: St.Gabriel's",
      "type": "sports",
      "classes": [
        "IA",
        "IB",
        "IIA",
        "IIB",
        "IIIA",
        "IIIB",
        "IVA",
        "IVB"
      ],
      "groupId": null,
      "rangeStart": null,
      "rangeEnd": null,
      "rangePosition": null
    },
    {
      "id": 14,
      "date": "2026-07-25",
      "time": "",
      "title": "Bilateral: Wenlock",
      "type": "sports",
      "classes": [
        "5A",
        "5B",
        "6A",
        "6B",
        "7A",
        "7B",
        "8A",
        "8B"
      ],
      "groupId": null,
      "rangeStart": null,
      "rangeEnd": null,
      "rangePosition": null
    },
    {
      "id": 15,
      "date": "2026-07-25",
      "time": "",
      "title": "Bilateral: Wenlock",
      "type": "sports",
      "classes": [
        "IA",
        "IB",
        "IIA",
        "IIB",
        "IIIA",
        "IIIB",
        "IVA",
        "IVB"
      ],
      "groupId": null,
      "rangeStart": null,
      "rangeEnd": null,
      "rangePosition": null
    },
    {
      "id": 16,
      "date": "2026-08-01",
      "time": "",
      "title": "Bilateral: Dunalastair Peñ",
      "type": "sports",
      "classes": [
        "5A",
        "5B",
        "6A",
        "6B",
        "7A",
        "7B",
        "8A",
        "8B"
      ],
      "groupId": null,
      "rangeStart": null,
      "rangeEnd": null,
      "rangePosition": null
    },
    {
      "id": 17,
      "date": "2026-08-01",
      "time": "",
      "title": "Bilateral: Dunalastair Peñ",
      "type": "sports",
      "classes": [
        "IA",
        "IB",
        "IIA",
        "IIB",
        "IIIA",
        "IIIB",
        "IVA",
        "IVB"
      ],
      "groupId": null,
      "rangeStart": null,
      "rangeEnd": null,
      "rangePosition": null
    },
    {
      "id": 18,
      "date": "2026-08-08",
      "time": "",
      "title": "Festival de fútbol y voleibol",
      "type": "sports",
      "classes": [
        "3A",
        "3B",
        "4A",
        "4B"
      ],
      "groupId": null,
      "rangeStart": null,
      "rangeEnd": null,
      "rangePosition": null
    },
    {
      "id": 19,
      "date": "2026-08-16",
      "time": "",
      "title": "Viaje a Argentina",
      "type": "salida",
      "classes": [
        "7A",
        "7B"
      ],
      "groupId": "g1777554132519",
      "rangeStart": "2026-08-17",
      "rangeEnd": "2026-08-23",
      "rangePosition": "start"
    },
    {
      "id": 20,
      "date": "2026-08-17",
      "time": "",
      "title": "Viaje a Argentina",
      "type": "salida",
      "classes": [
        "7A",
        "7B"
      ],
      "groupId": "g1777554132519",
      "rangeStart": "2026-08-17",
      "rangeEnd": "2026-08-23",
      "rangePosition": "mid"
    },
    {
      "id": 21,
      "date": "2026-08-18",
      "time": "",
      "title": "Viaje a Argentina",
      "type": "salida",
      "classes": [
        "7A",
        "7B"
      ],
      "groupId": "g1777554132519",
      "rangeStart": "2026-08-17",
      "rangeEnd": "2026-08-23",
      "rangePosition": "mid"
    },
    {
      "id": 22,
      "date": "2026-08-19",
      "time": "",
      "title": "Viaje a Argentina",
      "type": "salida",
      "classes": [
        "7A",
        "7B"
      ],
      "groupId": "g1777554132519",
      "rangeStart": "2026-08-17",
      "rangeEnd": "2026-08-23",
      "rangePosition": "mid"
    },
    {
      "id": 23,
      "date": "2026-08-20",
      "time": "",
      "title": "Viaje a Argentina",
      "type": "salida",
      "classes": [
        "7A",
        "7B"
      ],
      "groupId": "g1777554132519",
      "rangeStart": "2026-08-17",
      "rangeEnd": "2026-08-23",
      "rangePosition": "mid"
    },
    {
      "id": 24,
      "date": "2026-08-21",
      "time": "",
      "title": "Viaje a Argentina",
      "type": "salida",
      "classes": [
        "7A",
        "7B"
      ],
      "groupId": "g1777554132519",
      "rangeStart": "2026-08-17",
      "rangeEnd": "2026-08-23",
      "rangePosition": "mid"
    },
    {
      "id": 25,
      "date": "2026-08-22",
      "time": "",
      "title": "Viaje a Argentina",
      "type": "salida",
      "classes": [
        "7A",
        "7B"
      ],
      "groupId": "g1777554132519",
      "rangeStart": "2026-08-17",
      "rangeEnd": "2026-08-23",
      "rangePosition": "end"
    },
    {
      "id": 26,
      "date": "2026-08-22",
      "time": "",
      "title": "Festival fútbol y voleibol",
      "type": "sports",
      "classes": [
        "5A",
        "5B",
        "6A",
        "6B"
      ],
      "groupId": null,
      "rangeStart": null,
      "rangeEnd": null,
      "rangePosition": null
    },
    {
      "id": 27,
      "date": "2026-08-28",
      "time": "",
      "title": "Torneo: Fútbol y voleibol",
      "type": "sports",
      "classes": [
        "IA",
        "IB",
        "IIA",
        "IIB",
        "IIIA",
        "IIIB",
        "IVA",
        "IVB"
      ],
      "groupId": null,
      "rangeStart": null,
      "rangeEnd": null,
      "rangePosition": null
    },
    {
      "id": 28,
      "date": "2026-08-29",
      "time": "",
      "title": "Torneo: Fútbol y voleibol",
      "type": "sports",
      "classes": [
        "7A",
        "7B",
        "8A",
        "8B"
      ],
      "groupId": null,
      "rangeStart": null,
      "rangeEnd": null,
      "rangePosition": null
    },
    {
      "id": 29,
      "date": "2026-10-03",
      "time": "",
      "title": "Bilateral: Fut.fem/Voley.masc Dunalastair",
      "type": "sports",
      "classes": [
        "5A",
        "5B",
        "6A",
        "6B",
        "7A",
        "7B",
        "8A",
        "8B"
      ],
      "groupId": null,
      "rangeStart": null,
      "rangeEnd": null,
      "rangePosition": null
    },
    {
      "id": 30,
      "date": "2026-10-03",
      "time": "",
      "title": "Bilateral: Fut.fem/Voley.masc Dunalastair",
      "type": "sports",
      "classes": [
        "IA",
        "IB",
        "IIA",
        "IIB",
        "IIIA",
        "IIIB",
        "IVA",
        "IVB"
      ],
      "groupId": null,
      "rangeStart": null,
      "rangeEnd": null,
      "rangePosition": null
    },
    {
      "id": 31,
      "date": "2026-10-10",
      "time": "",
      "title": "Bilateral: Wenlock",
      "type": "sports",
      "classes": [
        "IA",
        "IB",
        "IIA",
        "IIB",
        "IIIA",
        "IIIB",
        "IVA",
        "IVB"
      ],
      "groupId": null,
      "rangeStart": null,
      "rangeEnd": null,
      "rangePosition": null
    },
    {
      "id": 32,
      "date": "2026-10-17",
      "time": "",
      "title": "Bilateral: Dunalastair",
      "type": "sports",
      "classes": [
        "5A",
        "5B",
        "6A",
        "6B",
        "7A",
        "7B",
        "8A",
        "8B"
      ],
      "groupId": null,
      "rangeStart": null,
      "rangeEnd": null,
      "rangePosition": null
    },
    {
      "id": 33,
      "date": "2026-10-17",
      "time": "",
      "title": "Bilateral: Dunalastair",
      "type": "sports",
      "classes": [
        "IA",
        "IB",
        "IIA",
        "IIB",
        "IIIA",
        "IIIB",
        "IVA",
        "IVB"
      ],
      "groupId": null,
      "rangeStart": null,
      "rangeEnd": null,
      "rangePosition": null
    },
    {
      "id": 34,
      "date": "2026-10-23",
      "time": "",
      "title": "Torneo: Futbol damas",
      "type": "sports",
      "classes": [
        "7A",
        "7B",
        "8A",
        "8B"
      ],
      "groupId": null,
      "rangeStart": null,
      "rangeEnd": null,
      "rangePosition": null
    },
    {
      "id": 35,
      "date": "2026-10-24",
      "time": "",
      "title": "Torneo:Fut.Damas/Voleibol.Masc:",
      "type": "sports",
      "classes": [
        "IA",
        "IB",
        "IIA",
        "IIB",
        "IIIA",
        "IIIB",
        "IVA",
        "IVB"
      ],
      "groupId": null,
      "rangeStart": null,
      "rangeEnd": null,
      "rangePosition": null
    },
    {
      "id": 36,
      "date": "2026-11-14",
      "time": "",
      "title": "Festival Atletismo",
      "type": "sports",
      "classes": [
        "3A",
        "3B",
        "4A",
        "4B"
      ],
      "groupId": null,
      "rangeStart": null,
      "rangeEnd": null,
      "rangePosition": null
    },
    {
      "id": 37,
      "date": "2026-11-21",
      "time": "",
      "title": "Festival atletismo",
      "type": "sports",
      "classes": [
        "5A",
        "5B",
        "6A",
        "6B"
      ],
      "groupId": null,
      "rangeStart": null,
      "rangeEnd": null,
      "rangePosition": null
    },
    {
      "id": 38,
      "date": "2026-11-27",
      "time": "",
      "title": "Torneo Atletismo",
      "type": "sports",
      "classes": [
        "7A",
        "7B",
        "8A",
        "8B"
      ],
      "groupId": null,
      "rangeStart": null,
      "rangeEnd": null,
      "rangePosition": null
    },
    {
      "id": 40,
      "date": "2026-07-03",
      "time": "",
      "title": "CAS: Café concert",
      "type": "activity",
      "classes": [
        "PK",
        "K",
        "1A",
        "1B",
        "2A",
        "2B",
        "3A",
        "3B",
        "4A",
        "4B",
        "5A",
        "5B",
        "6A",
        "6B",
        "7A",
        "7B",
        "8A",
        "8B",
        "IA",
        "IB",
        "IIA",
        "IIB",
        "IIIA",
        "IIIB",
        "IVA",
        "IVB"
      ],
      "groupId": null,
      "rangeStart": null,
      "rangeEnd": null,
      "rangePosition": null
    },
    {
      "id": 41,
      "date": "2026-08-07",
      "time": "",
      "title": "CAS:Tallarinata",
      "type": "activity",
      "classes": [
        "PK",
        "K",
        "1A",
        "1B",
        "2A",
        "2B",
        "3A",
        "3B",
        "4A",
        "4B",
        "5A",
        "5B",
        "6A",
        "6B",
        "7A",
        "7B",
        "8A",
        "8B",
        "IA",
        "IB",
        "IIA",
        "IIB",
        "IIIA",
        "IIIB",
        "IVA",
        "IVB"
      ],
      "groupId": null,
      "rangeStart": null,
      "rangeEnd": null,
      "rangePosition": null
    },
    {
      "id": 57,
      "date": "2026-05-12",
      "time": "",
      "title": "Día de la Mujer Matemática",
      "type": "activity",
      "classes": [
        "5A",
        "5B",
        "6A",
        "6B",
        "7A",
        "7B",
        "8A",
        "8B"
      ],
      "groupId": null,
      "rangeStart": null,
      "rangeEnd": null,
      "rangePosition": null
    },
    {
      "id": 58,
      "date": "2026-05-12",
      "time": "",
      "title": "Día de la Mujer Matemática",
      "type": "activity",
      "classes": [
        "IA",
        "IB",
        "IIA",
        "IIB",
        "IIIA",
        "IIIB",
        "IVA",
        "IVB"
      ],
      "groupId": null,
      "rangeStart": null,
      "rangeEnd": null,
      "rangePosition": null
    },
    {
      "id": 59,
      "date": "2026-05-14",
      "time": "",
      "title": "Salida Isla Negra (Lenguaje)",
      "type": "salida",
      "classes": [
        "IIA",
        "IIB"
      ],
      "groupId": null,
      "rangeStart": null,
      "rangeEnd": null,
      "rangePosition": null
    },
    {
      "id": 60,
      "date": "2026-06-26",
      "time": "",
      "title": "Salida Santiago Centro",
      "type": "salida",
      "classes": [
        "IVA",
        "IVB"
      ],
      "groupId": null,
      "rangeStart": null,
      "rangeEnd": null,
      "rangePosition": null
    },
    {
      "id": 61,
      "date": "2026-08-08",
      "time": "",
      "title": "Matemática e Ingenio 2026 (The Mackay School)",
      "type": "salida",
      "classes": [
        "5A",
        "5B",
        "6A",
        "6B",
        "7A",
        "7B",
        "8A",
        "8B"
      ],
      "groupId": null,
      "rangeStart": null,
      "rangeEnd": null,
      "rangePosition": null
    },
    {
      "id": 62,
      "date": "2026-08-08",
      "time": "",
      "title": "Matemática e Ingenio 2026 (The Mackay School)",
      "type": "salida",
      "classes": [
        "IA",
        "IB",
        "IIA",
        "IIB"
      ],
      "groupId": null,
      "rangeStart": null,
      "rangeEnd": null,
      "rangePosition": null
    },
    {
      "id": 63,
      "date": "2026-08-10",
      "time": "",
      "title": "Encuentro de Lírica (Mackay)",
      "type": "salida",
      "classes": [
        "5A",
        "5B",
        "6A",
        "6B",
        "7A",
        "7B",
        "8A",
        "8B"
      ],
      "groupId": null,
      "rangeStart": null,
      "rangeEnd": null,
      "rangePosition": null
    },
    {
      "id": 64,
      "date": "2026-08-10",
      "time": "",
      "title": "Encuentro de Lírica (Mackay)",
      "type": "salida",
      "classes": [
        "IA",
        "IB",
        "IIA",
        "IIB",
        "IIIA",
        "IIIB",
        "IVA",
        "IVB"
      ],
      "groupId": null,
      "rangeStart": null,
      "rangeEnd": null,
      "rangePosition": null
    },
    {
      "id": 65,
      "date": "2026-10-23",
      "time": "",
      "title": "Encuentro Debate",
      "type": "activity",
      "classes": [
        "8A",
        "8B"
      ],
      "groupId": null,
      "rangeStart": null,
      "rangeEnd": null,
      "rangePosition": null
    },
    {
      "id": 66,
      "date": "2026-10-23",
      "time": "",
      "title": "Encuentro Debate",
      "type": "activity",
      "classes": [
        "IA",
        "IB",
        "IIA",
        "IIB"
      ],
      "groupId": null,
      "rangeStart": null,
      "rangeEnd": null,
      "rangePosition": null
    },
    {
      "id": 67,
      "date": "2026-12-11",
      "time": "",
      "title": "Mundo de Religiones",
      "type": "salida",
      "classes": [
        "7A",
        "7B"
      ],
      "groupId": null,
      "rangeStart": null,
      "rangeEnd": null,
      "rangePosition": null
    },
    {
      "id": 70,
      "date": "2026-05-28",
      "time": "",
      "title": "Talleres ACHBI (sin clases)",
      "type": "cross",
      "classes": [],
      "groupId": "g1777556936938",
      "rangeStart": "2026-05-28",
      "rangeEnd": "2026-05-30",
      "rangePosition": "start"
    },
    {
      "id": 71,
      "date": "2026-05-29",
      "time": "",
      "title": "Talleres ACHBI (sin clases)",
      "type": "cross",
      "classes": [],
      "groupId": "g1777556936938",
      "rangeStart": "2026-05-28",
      "rangeEnd": "2026-05-30",
      "rangePosition": "mid"
    },
    {
      "id": 72,
      "date": "2026-05-30",
      "time": "",
      "title": "Talleres ACHBI (sin clases)",
      "type": "cross",
      "classes": [],
      "groupId": "g1777556936938",
      "rangeStart": "2026-05-28",
      "rangeEnd": "2026-05-30",
      "rangePosition": "end"
    },
    {
      "id": 87,
      "date": "2026-11-26",
      "time": "",
      "title": "PYP Exhibition",
      "type": "activity",
      "classes": [
        "4A",
        "4B"
      ],
      "groupId": null,
      "rangeStart": null,
      "rangeEnd": null,
      "rangePosition": null
    },
    {
      "id": 88,
      "date": "2026-11-27",
      "time": "",
      "title": "8th Grade Final Ceremony",
      "type": "activity",
      "classes": [
        "8A",
        "8B"
      ],
      "groupId": null,
      "rangeStart": null,
      "rangeEnd": null,
      "rangePosition": null
    },
    {
      "id": 89,
      "date": "2026-10-30",
      "time": "",
      "title": "IV Last Assembly",
      "type": "activity",
      "classes": [
        "IVA",
        "IVB"
      ],
      "groupId": null,
      "rangeStart": null,
      "rangeEnd": null,
      "rangePosition": null
    },
    {
      "id": 90,
      "date": "2026-12-09",
      "time": "",
      "title": "Senior: End-of-Year Ceremony",
      "type": "activity",
      "classes": [
        "IA",
        "IB",
        "IIA",
        "IIB",
        "IIIA",
        "IIIB",
        "IVA",
        "IVB"
      ],
      "groupId": null,
      "rangeStart": null,
      "rangeEnd": null,
      "rangePosition": null
    },
    {
      "id": 91,
      "date": "2026-12-03",
      "time": "",
      "title": "End-of-year Ceremony K 7pm",
      "type": "activity",
      "classes": [
        "K"
      ],
      "groupId": null,
      "rangeStart": null,
      "rangeEnd": null,
      "rangePosition": null
    },
    {
      "id": 92,
      "date": "2026-12-02",
      "time": "",
      "title": "End-of-year Ceremony 3/4 8.30am",
      "type": "activity",
      "classes": [
        "3A",
        "3B",
        "4A",
        "4B"
      ],
      "groupId": null,
      "rangeStart": null,
      "rangeEnd": null,
      "rangePosition": null
    },
    {
      "id": 93,
      "date": "2026-12-01",
      "time": "",
      "title": "End-of-year Ceremony 1/2 8.30am",
      "type": "activity",
      "classes": [
        "1A",
        "1B",
        "2A",
        "2B"
      ],
      "groupId": null,
      "rangeStart": null,
      "rangeEnd": null,
      "rangePosition": null
    },
    {
      "id": 94,
      "date": "2026-12-10",
      "time": "",
      "title": "End-of-year Ceremony Middle",
      "type": "activity",
      "classes": [
        "5A",
        "5B",
        "6A",
        "6B",
        "7A",
        "7B",
        "8A",
        "8B"
      ],
      "groupId": null,
      "rangeStart": null,
      "rangeEnd": null,
      "rangePosition": null
    },
    {
      "id": 95,
      "date": "2026-12-11",
      "time": "",
      "title": "Graduation Ceremony 7pm",
      "type": "activity",
      "classes": [
        "IVA",
        "IVB"
      ],
      "groupId": null,
      "rangeStart": null,
      "rangeEnd": null,
      "rangePosition": null
    },
    {
      "id": 96,
      "date": "2026-10-24",
      "time": "",
      "title": "Primera Comunión",
      "type": "activity",
      "classes": [
        "4A",
        "4B"
      ],
      "groupId": null,
      "rangeStart": null,
      "rangeEnd": null,
      "rangePosition": null
    },
    {
      "id": 97,
      "date": "2026-10-19",
      "time": "",
      "title": "Community Celebration TBC",
      "type": "cross",
      "classes": [],
      "groupId": "g1777557676471",
      "rangeStart": "2026-10-20",
      "rangeEnd": "2026-10-22",
      "rangePosition": "start"
    },
    {
      "id": 98,
      "date": "2026-10-20",
      "time": "",
      "title": "Community Celebration TBC",
      "type": "cross",
      "classes": [],
      "groupId": "g1777557676471",
      "rangeStart": "2026-10-20",
      "rangeEnd": "2026-10-22",
      "rangePosition": "mid"
    },
    {
      "id": 99,
      "date": "2026-10-21",
      "time": "",
      "title": "Community Celebration TBC",
      "type": "cross",
      "classes": [],
      "groupId": "g1777557676471",
      "rangeStart": "2026-10-20",
      "rangeEnd": "2026-10-22",
      "rangePosition": "end"
    },
    {
      "id": 100,
      "date": "2026-11-13",
      "time": "",
      "title": "Velada Literaria",
      "type": "cross",
      "classes": [],
      "groupId": null,
      "rangeStart": null,
      "rangeEnd": null,
      "rangePosition": null
    },
    {
      "id": 101,
      "date": "2026-09-29",
      "time": "",
      "title": "Chilenidad",
      "type": "activity",
      "classes": [
        "PK",
        "K",
        "1A",
        "1B",
        "2A",
        "2B",
        "3A",
        "3B",
        "4A",
        "4B"
      ],
      "groupId": null,
      "rangeStart": null,
      "rangeEnd": null,
      "rangePosition": null
    },
    {
      "id": 102,
      "date": "2026-09-23",
      "time": "",
      "title": "Chilenidad",
      "type": "activity",
      "classes": [
        "5A",
        "5B",
        "6A",
        "6B",
        "7A",
        "7B",
        "8A",
        "8B"
      ],
      "groupId": null,
      "rangeStart": null,
      "rangeEnd": null,
      "rangePosition": null
    },
    {
      "id": 103,
      "date": "2026-09-23",
      "time": "",
      "title": "Chilenidad",
      "type": "activity",
      "classes": [
        "IA",
        "IB",
        "IIA",
        "IIB",
        "IIIA",
        "IIIB",
        "IVA",
        "IVB"
      ],
      "groupId": null,
      "rangeStart": null,
      "rangeEnd": null,
      "rangePosition": null
    },
    {
      "id": 106,
      "date": "2026-05-27",
      "time": "",
      "title": "Tarde Trabajo Profesores",
      "type": "cross",
      "classes": [],
      "groupId": null,
      "rangeStart": null,
      "rangeEnd": null,
      "rangePosition": null
    },
    {
      "id": 107,
      "date": "2026-12-11",
      "time": "",
      "title": "Cierre de SchoolTrack",
      "type": "cross",
      "classes": [],
      "groupId": null,
      "rangeStart": null,
      "rangeEnd": null,
      "rangePosition": null
    },
    {
      "id": 108,
      "date": "2026-12-02",
      "time": "",
      "title": "Trabajo Profesores PM",
      "type": "cross",
      "classes": [],
      "groupId": null,
      "rangeStart": null,
      "rangeEnd": null,
      "rangePosition": null
    },
    {
      "id": 109,
      "date": "2026-11-12",
      "time": "",
      "title": "Confirmación",
      "type": "activity",
      "classes": [
        "IA",
        "IB",
        "IIA",
        "IIB",
        "IIIA",
        "IIIB",
        "IVA",
        "IVB"
      ],
      "groupId": null,
      "rangeStart": null,
      "rangeEnd": null,
      "rangePosition": null
    },
    {
      "id": 110,
      "date": "2026-10-14",
      "time": "",
      "title": "Feria PP",
      "type": "activity",
      "classes": [
        "IA",
        "IB"
      ],
      "groupId": null,
      "rangeStart": null,
      "rangeEnd": null,
      "rangePosition": null
    },
    {
      "id": 111,
      "date": "2026-07-15",
      "time": "",
      "title": "Parent-Teacher Day Junior",
      "type": "activity",
      "classes": [
        "PK",
        "K",
        "1A",
        "1B",
        "2A",
        "2B",
        "3A",
        "3B",
        "4A",
        "4B"
      ],
      "groupId": null,
      "rangeStart": null,
      "rangeEnd": null,
      "rangePosition": null
    },
    {
      "id": 112,
      "date": "2026-07-20",
      "time": "",
      "title": "II SEMESTRE",
      "type": "cross",
      "classes": [],
      "groupId": null,
      "rangeStart": null,
      "rangeEnd": null,
      "rangePosition": null
    },
    {
      "id": 113,
      "date": "2026-09-04",
      "time": "",
      "title": "School Anniversary",
      "type": "activity",
      "classes": [
        "PK",
        "K",
        "1A",
        "1B",
        "2A",
        "2B",
        "3A",
        "3B",
        "4A",
        "4B"
      ],
      "groupId": null,
      "rangeStart": null,
      "rangeEnd": null,
      "rangePosition": null
    },
    {
      "id": 114,
      "date": "2026-09-02",
      "time": "",
      "title": "School Anniversary",
      "type": "activity",
      "classes": [
        "5A",
        "5B",
        "6A",
        "6B",
        "7A",
        "7B",
        "8A",
        "8B"
      ],
      "groupId": "g1777558565160",
      "rangeStart": "2026-09-03",
      "rangeEnd": "2026-09-04",
      "rangePosition": "start"
    },
    {
      "id": 115,
      "date": "2026-09-03",
      "time": "",
      "title": "School Anniversary",
      "type": "activity",
      "classes": [
        "5A",
        "5B",
        "6A",
        "6B",
        "7A",
        "7B",
        "8A",
        "8B"
      ],
      "groupId": "g1777558565160",
      "rangeStart": "2026-09-03",
      "rangeEnd": "2026-09-04",
      "rangePosition": "end"
    },
    {
      "id": 116,
      "date": "2026-09-02",
      "time": "",
      "title": "School Anniversary",
      "type": "activity",
      "classes": [
        "IA",
        "IB",
        "IIA",
        "IIB",
        "IIIA",
        "IIIB",
        "IVA",
        "IVB"
      ],
      "groupId": "g1777558589949",
      "rangeStart": "2026-09-03",
      "rangeEnd": "2026-09-04",
      "rangePosition": "start"
    },
    {
      "id": 117,
      "date": "2026-09-03",
      "time": "",
      "title": "School Anniversary",
      "type": "activity",
      "classes": [
        "IA",
        "IB",
        "IIA",
        "IIB",
        "IIIA",
        "IIIB",
        "IVA",
        "IVB"
      ],
      "groupId": "g1777558589949",
      "rangeStart": "2026-09-03",
      "rangeEnd": "2026-09-04",
      "rangePosition": "end"
    },
    {
      "id": 118,
      "date": "2026-07-25",
      "time": "",
      "title": "Bilateral: Wenlock",
      "type": "activity",
      "classes": [
        "5A",
        "5B",
        "6A",
        "6B",
        "7A",
        "7B",
        "8A",
        "8B"
      ],
      "groupId": null,
      "rangeStart": null,
      "rangeEnd": null,
      "rangePosition": null
    },
    {
      "id": 119,
      "date": "2026-09-04",
      "time": "",
      "title": "Día del Alumno",
      "type": "activity",
      "classes": [
        "PK",
        "K",
        "1A",
        "1B",
        "2A",
        "2B",
        "3A",
        "3B",
        "4A",
        "4B",
        "5A",
        "5B",
        "6A",
        "6B",
        "7A",
        "7B",
        "8A",
        "8B",
        "IA",
        "IB",
        "IIA",
        "IIB",
        "IIIA",
        "IIIB",
        "IVA",
        "IVB"
      ],
      "groupId": null,
      "rangeStart": null,
      "rangeEnd": null,
      "rangePosition": null
    },
    {
      "id": 134,
      "date": "2026-05-21",
      "time": "",
      "title": "Feriado",
      "type": "feriado",
      "classes": [],
      "groupId": "g1777839610703",
      "rangeStart": "2026-05-21",
      "rangeEnd": "2026-05-22",
      "rangePosition": "start"
    },
    {
      "id": 135,
      "date": "2026-05-22",
      "time": "",
      "title": "Feriado",
      "type": "feriado",
      "classes": [],
      "groupId": "g1777839610703",
      "rangeStart": "2026-05-21",
      "rangeEnd": "2026-05-22",
      "rangePosition": "end"
    },
    {
      "id": 136,
      "date": "2026-06-01",
      "time": "",
      "title": "Vacaciones",
      "type": "feriado",
      "classes": [],
      "groupId": "g1777893717311",
      "rangeStart": "2026-06-01",
      "rangeEnd": "2026-06-12",
      "rangePosition": "start"
    },
    {
      "id": 137,
      "date": "2026-06-02",
      "time": "",
      "title": "Vacaciones",
      "type": "feriado",
      "classes": [],
      "groupId": "g1777893717311",
      "rangeStart": "2026-06-01",
      "rangeEnd": "2026-06-12",
      "rangePosition": "mid"
    },
    {
      "id": 138,
      "date": "2026-06-03",
      "time": "",
      "title": "Vacaciones",
      "type": "feriado",
      "classes": [],
      "groupId": "g1777893717311",
      "rangeStart": "2026-06-01",
      "rangeEnd": "2026-06-12",
      "rangePosition": "mid"
    },
    {
      "id": 139,
      "date": "2026-06-04",
      "time": "",
      "title": "Vacaciones",
      "type": "feriado",
      "classes": [],
      "groupId": "g1777893717311",
      "rangeStart": "2026-06-01",
      "rangeEnd": "2026-06-12",
      "rangePosition": "mid"
    },
    {
      "id": 140,
      "date": "2026-06-05",
      "time": "",
      "title": "Vacaciones",
      "type": "feriado",
      "classes": [],
      "groupId": "g1777893717311",
      "rangeStart": "2026-06-01",
      "rangeEnd": "2026-06-12",
      "rangePosition": "mid"
    },
    {
      "id": 141,
      "date": "2026-06-06",
      "time": "",
      "title": "Vacaciones",
      "type": "feriado",
      "classes": [],
      "groupId": "g1777893717311",
      "rangeStart": "2026-06-01",
      "rangeEnd": "2026-06-12",
      "rangePosition": "mid"
    },
    {
      "id": 143,
      "date": "2026-06-08",
      "time": "",
      "title": "Vacaciones",
      "type": "feriado",
      "classes": [],
      "groupId": "g1777893717311",
      "rangeStart": "2026-06-01",
      "rangeEnd": "2026-06-12",
      "rangePosition": "mid"
    },
    {
      "id": 144,
      "date": "2026-06-09",
      "time": "",
      "title": "Vacaciones",
      "type": "feriado",
      "classes": [],
      "groupId": "g1777893717311",
      "rangeStart": "2026-06-01",
      "rangeEnd": "2026-06-12",
      "rangePosition": "mid"
    },
    {
      "id": 145,
      "date": "2026-06-10",
      "time": "",
      "title": "Vacaciones",
      "type": "feriado",
      "classes": [],
      "groupId": "g1777893717311",
      "rangeStart": "2026-06-01",
      "rangeEnd": "2026-06-12",
      "rangePosition": "mid"
    },
    {
      "id": 146,
      "date": "2026-06-11",
      "time": "",
      "title": "Vacaciones",
      "type": "feriado",
      "classes": [],
      "groupId": "g1777893717311",
      "rangeStart": "2026-06-01",
      "rangeEnd": "2026-06-12",
      "rangePosition": "mid"
    },
    {
      "id": 147,
      "date": "2026-06-12",
      "time": "",
      "title": "Vacaciones",
      "type": "feriado",
      "classes": [],
      "groupId": "g1777893717311",
      "rangeStart": "2026-06-01",
      "rangeEnd": "2026-06-12",
      "rangePosition": "end"
    },
    {
      "id": 148,
      "date": "2026-09-07",
      "time": "",
      "title": "Vacaciones",
      "type": "feriado",
      "classes": [],
      "groupId": "g1777893838010",
      "rangeStart": "2026-09-07",
      "rangeEnd": "2026-09-18",
      "rangePosition": "start"
    },
    {
      "id": 149,
      "date": "2026-09-08",
      "time": "",
      "title": "Vacaciones",
      "type": "feriado",
      "classes": [],
      "groupId": "g1777893838010",
      "rangeStart": "2026-09-07",
      "rangeEnd": "2026-09-18",
      "rangePosition": "mid"
    },
    {
      "id": 150,
      "date": "2026-09-09",
      "time": "",
      "title": "Vacaciones",
      "type": "feriado",
      "classes": [],
      "groupId": "g1777893838010",
      "rangeStart": "2026-09-07",
      "rangeEnd": "2026-09-18",
      "rangePosition": "mid"
    },
    {
      "id": 151,
      "date": "2026-09-10",
      "time": "",
      "title": "Vacaciones",
      "type": "feriado",
      "classes": [],
      "groupId": "g1777893838010",
      "rangeStart": "2026-09-07",
      "rangeEnd": "2026-09-18",
      "rangePosition": "mid"
    },
    {
      "id": 152,
      "date": "2026-09-11",
      "time": "",
      "title": "Vacaciones",
      "type": "feriado",
      "classes": [],
      "groupId": "g1777893838010",
      "rangeStart": "2026-09-07",
      "rangeEnd": "2026-09-18",
      "rangePosition": "mid"
    },
    {
      "id": 153,
      "date": "2026-09-12",
      "time": "",
      "title": "Vacaciones",
      "type": "feriado",
      "classes": [],
      "groupId": "g1777893838010",
      "rangeStart": "2026-09-07",
      "rangeEnd": "2026-09-18",
      "rangePosition": "mid"
    },
    {
      "id": 154,
      "date": "2026-09-13",
      "time": "",
      "title": "Vacaciones",
      "type": "feriado",
      "classes": [],
      "groupId": "g1777893838010",
      "rangeStart": "2026-09-07",
      "rangeEnd": "2026-09-18",
      "rangePosition": "mid"
    },
    {
      "id": 155,
      "date": "2026-09-14",
      "time": "",
      "title": "Vacaciones",
      "type": "feriado",
      "classes": [],
      "groupId": "g1777893838010",
      "rangeStart": "2026-09-07",
      "rangeEnd": "2026-09-18",
      "rangePosition": "mid"
    },
    {
      "id": 156,
      "date": "2026-09-15",
      "time": "",
      "title": "Vacaciones",
      "type": "feriado",
      "classes": [],
      "groupId": "g1777893838010",
      "rangeStart": "2026-09-07",
      "rangeEnd": "2026-09-18",
      "rangePosition": "mid"
    },
    {
      "id": 157,
      "date": "2026-09-16",
      "time": "",
      "title": "Vacaciones",
      "type": "feriado",
      "classes": [],
      "groupId": "g1777893838010",
      "rangeStart": "2026-09-07",
      "rangeEnd": "2026-09-18",
      "rangePosition": "mid"
    },
    {
      "id": 158,
      "date": "2026-09-17",
      "time": "",
      "title": "Vacaciones",
      "type": "feriado",
      "classes": [],
      "groupId": "g1777893838010",
      "rangeStart": "2026-09-07",
      "rangeEnd": "2026-09-18",
      "rangePosition": "mid"
    },
    {
      "id": 159,
      "date": "2026-09-18",
      "time": "",
      "title": "Vacaciones",
      "type": "feriado",
      "classes": [],
      "groupId": "g1777893838010",
      "rangeStart": "2026-09-07",
      "rangeEnd": "2026-09-18",
      "rangePosition": "end"
    },
    {
      "id": 160,
      "date": "2026-05-14",
      "time": "",
      "title": "Drama & Literature event",
      "type": "activity",
      "classes": [
        "4A",
        "4B"
      ],
      "groupId": null,
      "rangeStart": null,
      "rangeEnd": null,
      "rangePosition": null
    },
    {
      "id": 161,
      "date": "2026-05-13",
      "time": "",
      "title": "Visita Museo Historia Natural",
      "type": "activity",
      "classes": [
        "2B"
      ],
      "groupId": null,
      "rangeStart": null,
      "rangeEnd": null,
      "rangePosition": null
    },
    {
      "id": 162,
      "date": "2026-06-18",
      "time": "",
      "title": "Visita Planetario USACH",
      "type": "activity",
      "classes": [
        "3A",
        "3B"
      ],
      "groupId": null,
      "rangeStart": null,
      "rangeEnd": null,
      "rangePosition": null
    },
    {
      "id": 163,
      "date": "2026-05-15",
      "time": "",
      "title": "Visita Buin Zoo",
      "type": "activity",
      "classes": [
        "1A",
        "1B"
      ],
      "groupId": null,
      "rangeStart": null,
      "rangeEnd": null,
      "rangePosition": null
    },
    {
      "id": 164,
      "date": "2026-07-13",
      "time": "",
      "title": "Comments and Grades uploaded in Schooltrack",
      "type": "activity",
      "classes": [
        "PK",
        "K",
        "1A",
        "1B",
        "2A",
        "2B",
        "3A",
        "3B",
        "4A",
        "4B"
      ],
      "groupId": null,
      "rangeStart": null,
      "rangeEnd": null,
      "rangePosition": null
    },
    {
      "id": 166,
      "date": "2026-07-08",
      "time": "",
      "title": "Consejo PK-K",
      "type": "activity",
      "classes": [
        "PK",
        "K"
      ],
      "groupId": null,
      "rangeStart": null,
      "rangeEnd": null,
      "rangePosition": null
    },
    {
      "id": 167,
      "date": "2026-07-14",
      "time": "",
      "title": "Día del alumno",
      "type": "activity",
      "classes": [
        "PK",
        "K",
        "1A",
        "1B",
        "2A",
        "2B",
        "3A",
        "3B",
        "4A",
        "4B"
      ],
      "groupId": null,
      "rangeStart": null,
      "rangeEnd": null,
      "rangePosition": null
    },
    {
      "id": 168,
      "date": "2026-06-24",
      "time": "",
      "title": "Consejo 3° y 4° Básico",
      "type": "activity",
      "classes": [
        "3A",
        "3B",
        "4A",
        "4B"
      ],
      "groupId": null,
      "rangeStart": null,
      "rangeEnd": null,
      "rangePosition": null
    },
    {
      "id": 169,
      "date": "2026-07-01",
      "time": "",
      "title": "Consejo 1° y 2°",
      "type": "activity",
      "classes": [
        "1A",
        "1B",
        "2A",
        "2B"
      ],
      "groupId": null,
      "rangeStart": null,
      "rangeEnd": null,
      "rangePosition": null
    },
    {
      "id": 170,
      "date": "2026-06-22",
      "time": "",
      "title": "SIN EVALUACIONES NI ENTREGAS",
      "type": "test",
      "classes": [
        "IA",
        "IB",
        "IIA",
        "IIB",
        "IIIA",
        "IIIB",
        "IVA",
        "IVB"
      ],
      "groupId": "g1777990371975",
      "rangeStart": "2026-06-22",
      "rangeEnd": "2026-06-23",
      "rangePosition": "start"
    },
    {
      "id": 171,
      "date": "2026-06-23",
      "time": "",
      "title": "SIN EVALUACIONES NI ENTREGAS",
      "type": "test",
      "classes": [
        "IA",
        "IB",
        "IIA",
        "IIB",
        "IIIA",
        "IIIB",
        "IVA",
        "IVB"
      ],
      "groupId": "g1777990371975",
      "rangeStart": "2026-06-22",
      "rangeEnd": "2026-06-23",
      "rangePosition": "end"
    },
    {
      "id": 174,
      "date": "2026-08-31",
      "time": "",
      "title": "SIN EVALUACIONES NI ENTREGAS",
      "type": "test",
      "classes": [
        "7A",
        "7B",
        "8A",
        "8B"
      ],
      "groupId": null,
      "rangeStart": null,
      "rangeEnd": null,
      "rangePosition": null
    },
    {
      "id": 175,
      "date": "2026-08-31",
      "time": "",
      "title": "SIN EVALUACIONES NI ENTREGAS",
      "type": "test",
      "classes": [
        "IA",
        "IB",
        "IIA",
        "IIB",
        "IIIA",
        "IIIB",
        "IVA",
        "IVB"
      ],
      "groupId": null,
      "rangeStart": null,
      "rangeEnd": null,
      "rangePosition": null
    },
    {
      "id": 176,
      "date": "2026-08-17",
      "time": "",
      "title": "SIN EVALUACIONES NI ENTREGAS",
      "type": "test",
      "classes": [
        "7A",
        "7B"
      ],
      "groupId": "g1777990768387",
      "rangeStart": "2026-08-17",
      "rangeEnd": "2026-08-24",
      "rangePosition": "start"
    },
    {
      "id": 177,
      "date": "2026-08-18",
      "time": "",
      "title": "SIN EVALUACIONES NI ENTREGAS",
      "type": "test",
      "classes": [
        "7A",
        "7B"
      ],
      "groupId": "g1777990768387",
      "rangeStart": "2026-08-17",
      "rangeEnd": "2026-08-24",
      "rangePosition": "mid"
    },
    {
      "id": 178,
      "date": "2026-08-19",
      "time": "",
      "title": "SIN EVALUACIONES NI ENTREGAS",
      "type": "test",
      "classes": [
        "7A",
        "7B"
      ],
      "groupId": "g1777990768387",
      "rangeStart": "2026-08-17",
      "rangeEnd": "2026-08-24",
      "rangePosition": "mid"
    },
    {
      "id": 179,
      "date": "2026-08-20",
      "time": "",
      "title": "SIN EVALUACIONES NI ENTREGAS",
      "type": "test",
      "classes": [
        "7A",
        "7B"
      ],
      "groupId": "g1777990768387",
      "rangeStart": "2026-08-17",
      "rangeEnd": "2026-08-24",
      "rangePosition": "mid"
    },
    {
      "id": 180,
      "date": "2026-08-21",
      "time": "",
      "title": "SIN EVALUACIONES NI ENTREGAS",
      "type": "test",
      "classes": [
        "7A",
        "7B"
      ],
      "groupId": "g1777990768387",
      "rangeStart": "2026-08-17",
      "rangeEnd": "2026-08-24",
      "rangePosition": "mid"
    },
    {
      "id": 181,
      "date": "2026-08-22",
      "time": "",
      "title": "SIN EVALUACIONES NI ENTREGAS",
      "type": "test",
      "classes": [
        "7A",
        "7B"
      ],
      "groupId": "g1777990768387",
      "rangeStart": "2026-08-17",
      "rangeEnd": "2026-08-24",
      "rangePosition": "mid"
    },
    {
      "id": 182,
      "date": "2026-08-23",
      "time": "",
      "title": "SIN EVALUACIONES NI ENTREGAS",
      "type": "test",
      "classes": [
        "7A",
        "7B"
      ],
      "groupId": "g1777990768387",
      "rangeStart": "2026-08-17",
      "rangeEnd": "2026-08-24",
      "rangePosition": "mid"
    },
    {
      "id": 183,
      "date": "2026-08-24",
      "time": "",
      "title": "SIN EVALUACIONES NI ENTREGAS",
      "type": "test",
      "classes": [
        "7A",
        "7B"
      ],
      "groupId": "g1777990768387",
      "rangeStart": "2026-08-17",
      "rangeEnd": "2026-08-24",
      "rangePosition": "end"
    },
    {
      "id": 184,
      "date": "2026-05-08",
      "time": "",
      "title": "SALIDA DESAFIOS",
      "type": "salida",
      "classes": [
        "IA",
        "IB"
      ],
      "groupId": null,
      "rangeStart": null,
      "rangeEnd": null,
      "rangePosition": null
    },
    {
      "id": 186,
      "date": "2026-05-13",
      "time": "",
      "title": "Consejos 14.45-16.45",
      "type": "activity",
      "classes": [
        "5A",
        "5B",
        "7A",
        "7B"
      ],
      "groupId": null,
      "rangeStart": null,
      "rangeEnd": null,
      "rangePosition": null
    },
    {
      "id": 189,
      "date": "2026-11-06",
      "time": "",
      "title": "Expo Internacional Proyectos MYP (Stgo College)",
      "type": "salida",
      "classes": [
        "IA",
        "IB"
      ],
      "groupId": null,
      "rangeStart": null,
      "rangeEnd": null,
      "rangePosition": null
    },
    {
      "id": 190,
      "date": "2026-10-01",
      "time": "",
      "title": "CAS Proyecto V",
      "type": "salida",
      "classes": [
        "IIIA",
        "IIIB",
        "IVA",
        "IVB"
      ],
      "groupId": "g1778160330157",
      "rangeStart": "2026-10-01",
      "rangeEnd": "2026-10-03",
      "rangePosition": "start"
    },
    {
      "id": 191,
      "date": "2026-10-02",
      "time": "",
      "title": "CAS Proyecto V",
      "type": "salida",
      "classes": [
        "IIIA",
        "IIIB",
        "IVA",
        "IVB"
      ],
      "groupId": "g1778160330157",
      "rangeStart": "2026-10-01",
      "rangeEnd": "2026-10-03",
      "rangePosition": "mid"
    },
    {
      "id": 192,
      "date": "2026-10-03",
      "time": "",
      "title": "CAS Proyecto V",
      "type": "salida",
      "classes": [
        "IIIA",
        "IIIB",
        "IVA",
        "IVB"
      ],
      "groupId": "g1778160330157",
      "rangeStart": "2026-10-01",
      "rangeEnd": "2026-10-03",
      "rangePosition": "end"
    },
    {
      "id": 193,
      "date": "2026-10-07",
      "time": "",
      "title": "Semana de la Ciencia: Feria Ciencias",
      "type": "activity",
      "classes": [
        "5A",
        "5B",
        "6A",
        "6B",
        "7A",
        "7B",
        "8A",
        "8B",
        "IA",
        "IB",
        "IIA",
        "IIB",
        "IIIA",
        "IIIB",
        "IVA",
        "IVB"
      ],
      "groupId": null,
      "rangeStart": null,
      "rangeEnd": null,
      "rangePosition": null
    },
    {
      "id": 194,
      "date": "2026-10-08",
      "time": "",
      "title": "Semana de la Ciencia: Competencias",
      "type": "activity",
      "classes": [
        "5A",
        "5B",
        "6A",
        "6B",
        "7A",
        "7B",
        "8A",
        "8B",
        "IA",
        "IB",
        "IIA",
        "IIB",
        "IIIA",
        "IIIB",
        "IVA",
        "IVB"
      ],
      "groupId": null,
      "rangeStart": null,
      "rangeEnd": null,
      "rangePosition": null
    },
    {
      "id": 197,
      "date": "2026-10-09",
      "time": "",
      "title": "Semana de la Ciencia: Assembly",
      "type": "activity",
      "classes": [
        "5A",
        "5B",
        "6A",
        "6B",
        "7A",
        "7B",
        "8A",
        "8B"
      ],
      "groupId": null,
      "rangeStart": null,
      "rangeEnd": null,
      "rangePosition": null
    },
    {
      "id": 200,
      "date": "2026-10-09",
      "time": "",
      "title": "Semana de la Ciencia: Assembly",
      "type": "activity",
      "classes": [
        "IA",
        "IB",
        "IIA",
        "IIB",
        "IIIA",
        "IIIB",
        "IVA",
        "IVB"
      ],
      "groupId": null,
      "rangeStart": null,
      "rangeEnd": null,
      "rangePosition": null
    },
    {
      "id": 201,
      "date": "2026-10-09",
      "time": "",
      "title": "Semana de la Ciencia: Lanzamiento globo",
      "type": "activity",
      "classes": [
        "5A",
        "5B",
        "6A",
        "6B",
        "7A",
        "7B",
        "8A",
        "8B",
        "IA",
        "IB",
        "IIA",
        "IIB",
        "IIIA",
        "IIIB",
        "IVA",
        "IVB"
      ],
      "groupId": null,
      "rangeStart": null,
      "rangeEnd": null,
      "rangePosition": null
    },
    {
      "id": 202,
      "date": "2026-08-12",
      "time": "",
      "title": "Festival de la Voz",
      "type": "cross",
      "classes": [],
      "groupId": null,
      "rangeStart": null,
      "rangeEnd": null,
      "rangePosition": null
    },
    {
      "id": 188,
      "date": "2026-06-17",
      "time": "",
      "title": "PM:Taller Psicopedagogía",
      "type": "activity",
      "classes": [
        "5A",
        "5B",
        "6A",
        "6B",
        "7A",
        "7B",
        "8A",
        "8B"
      ],
      "groupId": null,
      "rangeStart": null,
      "rangeEnd": null,
      "rangePosition": null
    },
    {
      "id": 187,
      "date": "2026-05-20",
      "time": "",
      "title": "Consejos 14.45-16.45",
      "type": "activity",
      "classes": [
        "6A",
        "6B",
        "8A",
        "8B"
      ],
      "groupId": null,
      "rangeStart": null,
      "rangeEnd": null,
      "rangePosition": null
    },
    {
      "id": 203,
      "date": "2026-05-15",
      "time": "",
      "title": "Assembly: Responsabilidad penal",
      "type": "activity",
      "classes": [
        "5A",
        "5B",
        "6A",
        "6B",
        "7A",
        "7B",
        "8A",
        "8B"
      ],
      "groupId": null,
      "rangeStart": null,
      "rangeEnd": null,
      "rangePosition": null
    },
    {
      "id": 204,
      "date": "2026-05-15",
      "time": "",
      "title": "Assembly: Responsabilidad penal",
      "type": "activity",
      "classes": [
        "IA",
        "IB",
        "IIA",
        "IIB",
        "IIIA",
        "IIIB",
        "IVA",
        "IVB"
      ],
      "groupId": null,
      "rangeStart": null,
      "rangeEnd": null,
      "rangePosition": null
    },
    {
      "id": 205,
      "date": "2026-05-16",
      "time": "",
      "title": "CMAT- Matemáticas",
      "type": "salida",
      "classes": [
        "8A",
        "8B"
      ],
      "groupId": null,
      "rangeStart": null,
      "rangeEnd": null,
      "rangePosition": null
    },
    {
      "id": 39,
      "date": "2026-05-09",
      "time": "",
      "title": "CAS: Family Run",
      "type": "activity",
      "classes": [
        "PK",
        "K",
        "1A",
        "1B",
        "2A",
        "2B",
        "3A",
        "3B",
        "4A",
        "4B",
        "5A",
        "5B",
        "6A",
        "6B",
        "7A",
        "7B",
        "8A",
        "8B",
        "IA",
        "IB",
        "IIA",
        "IIB",
        "IIIA",
        "IIIB",
        "IVA",
        "IVB"
      ],
      "groupId": null,
      "rangeStart": null,
      "rangeEnd": null,
      "rangePosition": null
    },
    {
      "id": 105,
      "date": "2026-10-12",
      "time": "",
      "title": "Feriado",
      "type": "feriado",
      "classes": [],
      "groupId": null,
      "rangeStart": null,
      "rangeEnd": null,
      "rangePosition": null
    },
    {
      "id": 104,
      "date": "2026-10-16",
      "time": "",
      "title": "Dia del Profesor (Sin clases)",
      "type": "feriado",
      "classes": [],
      "groupId": null,
      "rangeStart": null,
      "rangeEnd": null,
      "rangePosition": null
    }
  ],
  "nextId": 206
}
